README.md
setup.py
power_api/__init__.py
power_api/command.py
power_api/definitions.py
power_api/event.py
power_api/exceptions.py
power_api/power_api.py
power_api.egg-info/PKG-INFO
power_api.egg-info/SOURCES.txt
power_api.egg-info/dependency_links.txt
power_api.egg-info/requires.txt
power_api.egg-info/top_level.txt